<?xml version="1.0"?>
<Printer Id="PDF" Version="1.0">
  <Name>Create a PDF document</Name>
  <Name xml:lang="bg">Създай PDF документ</Name>
  <Name xml:lang="ca">Crea un document PDF</Name>
  <Name xml:lang="cs">Vytvořit dokument PDF</Name>
  <Name xml:lang="da">Opret et PDF-dokument</Name>
  <Name xml:lang="de">Ein PDF-Dokument erstellen</Name>
  <Name xml:lang="el">Δημιουργία εγγράφου PDF</Name>
  <Name xml:lang="es">Crear un documento PDF</Name>
  <Name xml:lang="fi">Luo PDF-asiakirja</Name>
  <Name xml:lang="fr">Créer un document PDF</Name>
  <Name xml:lang="he">צור מסמך PDF</Name>
  <Name xml:lang="hu">PDF-dokumentum létrehozása</Name>
  <Name xml:lang="it">Crea un documento PDF</Name>
  <Name xml:lang="ja">PDF ドキュメントの作成</Name>
  <Name xml:lang="ko">PDF 문서 만들기</Name>
  <Name xml:lang="lv">Izveidot PDF dokumentu</Name>
  <Name xml:lang="mn">PDF-баримт үүсгэх</Name>
  <Name xml:lang="nl">Een PDF-document maken</Name>
  <Name xml:lang="no">Opprett ett PDF-dokument</Name>
  <Name xml:lang="pl">Utworzenie dokumentu PDF</Name>
  <Name xml:lang="pt">Criar um documento PDF</Name>
  <Name xml:lang="pt_BR">Criar um documento PDF</Name>
  <Name xml:lang="ro">Creează un document PDF</Name>
  <Name xml:lang="sk">Vytvoriť PDF dokument</Name>
  <Name xml:lang="sl">Ustvari dokument PDF</Name>
  <Name xml:lang="sv">Skapa ett PDF-dokument</Name>
  <Name xml:lang="tr">PDF belgesi yarat</Name>
  <Name xml:lang="uk">Створити документ у форматі PDF</Name>
  <Name xml:lang="vi">Tạo tài liệu PDF</Name>
  <Name xml:lang="zh_CN">创建 PDF 文档</Name>
  <Name xml:lang="zh_TW">製作 PDF 文件</Name>
  <Model>GNOME-PDF-WRITER</Model>
  <Settings Id="SETTINGS-000123456789123456789012">
    <Name>Default</Name>
    <Key Id="Engine">
      <Key Id="Backend" Value="gnome"/>
    </Key>
    <Key Id="Output">
      <Key Id="Media">
        <Key Id="PhysicalSize" Value="USLetter"/>
      </Key>
      <Key Id="Resolution" Value="360x360"/>
    </Key>
    <Key Id="Transport">
      <Key Id="Backend" Value="file"/>
    </Key>
  </Settings>
</Printer>
